LICENSE.txt
README.md
setup.cfg
setup.py
consolebox/__init__.py
consolebox/box.py
consolebox/checkbox.py
consolebox/item.py
consolebox/itemlist.py
consolebox/keyboard.py
consolebox/keylist.py
consolebox/menubox.py
consolebox/selectbox.py
consolebox/style.py
consolebox.egg-info/PKG-INFO
consolebox.egg-info/SOURCES.txt
consolebox.egg-info/dependency_links.txt
consolebox.egg-info/top_level.txt