Metadata-Version: 2.1
Name: consolebox
Version: 0.6.2
Summary: Package to create interactive menus and console interfaces -> https://github.com/JordyM01/consolebox
Home-page: https://github.com/JordyM01/consolebox
Author: JordyM01
Author-email: montoyamjavier@gmail.com
License: LGPL v3
Download-URL: https://github.com/JordyM01/consolebox/archive/refs/tags/v0.4.tar.gz
Platform: UNKNOWN
License-File: LICENSE.txt
